embedding_optimizer/__init__.py
embedding_optimizer/optimizer.py
embedding_optimizer-0.0.6.dist-info/LICENCE
embedding_optimizer-0.0.6.dist-info/METADATA
embedding_optimizer-0.0.6.dist-info/WHEEL
embedding_optimizer-0.0.6.dist-info/top_level.txt
embedding_optimizer-0.0.6.dist-info/RECORD
