Metadata-Version: 2.1
Name: embedding-optimizer
Version: 0.0.6
Summary: Strategies for Efficient Data Embedding: Creating Embeddings Optimized for Accuracy - Creating Embeddings Optimized for Storage
Home-page: https://github.com/taherfattahi/embedding-optimizer
Author: Taher Fattahi
Author-email: taherfattahi11@gmail.com
License: MIT
License-File: LICENCE
